jakecipher/__init__.py
jakecipher-0.1.4.dist-info/LICENSE
jakecipher-0.1.4.dist-info/METADATA
jakecipher-0.1.4.dist-info/WHEEL
jakecipher-0.1.4.dist-info/top_level.txt
jakecipher-0.1.4.dist-info/RECORD
