Metadata-Version: 2.1
Name: jakecipher
Version: 0.1.4
Summary: jake cipher algorithm
Home-page: https://github.com/crazyj7/pythonpack/tree/master/jakecipher
Author: crazyj
Author-email: crazyj7@gmail.com
License: MIT
Platform: UNKNOWN
Classifier: Programming Language :: Python :: 3
Classifier: License :: OSI Approved :: MIT License
Classifier: Operating System :: OS Independent
Requires-Python: >=3.6
Requires-Dist: numpy
